LICENSE
MANIFEST.in
README.md
setup.py
bin/roboger-control
roboger/__init__.py
roboger/api.py
roboger/core.py
roboger/server.py
roboger.egg-info/PKG-INFO
roboger.egg-info/SOURCES.txt
roboger.egg-info/dependency_links.txt
roboger.egg-info/requires.txt
roboger.egg-info/top_level.txt
roboger/plugins/__init__.py
roboger/plugins/android/__init__.py
roboger/plugins/chain/__init__.py
roboger/plugins/email/__init__.py
roboger/plugins/shell/__init__.py
roboger/plugins/slack/__init__.py
roboger/plugins/telegram/__init__.py
roboger/plugins/webhook/__init__.py
roboger/resources/sql/addr.create.sql
roboger/resources/sql/addr.delete.sql
roboger/resources/sql/addr.get.sql
roboger/resources/sql/addr.list.sql
roboger/resources/sql/addr.update.a.sql
roboger/resources/sql/addr.update.active.sql
roboger/resources/sql/addr.update.lim_c.sql
roboger/resources/sql/addr.update.lim_s.sql
roboger/resources/sql/bucket.cleanup.sql
roboger/resources/sql/bucket.cleanup:mysql.sql
roboger/resources/sql/bucket.cleanup:sqlite.sql
roboger/resources/sql/bucket.create.sql
roboger/resources/sql/bucket.delete.sql
roboger/resources/sql/bucket.get.sql
roboger/resources/sql/bucket.get:mysql.sql
roboger/resources/sql/bucket.get:sqlite.sql
roboger/resources/sql/bucket.touch.sql
roboger/resources/sql/del.sql
roboger/resources/sql/endpoint.create.sql
roboger/resources/sql/endpoint.delete.sql
roboger/resources/sql/endpoint.deletesub.sql
roboger/resources/sql/endpoint.get.sql
roboger/resources/sql/endpoint.list.sql
roboger/resources/sql/endpoint.update.sql
roboger/resources/sql/push.sql
roboger/resources/sql/subscription.create.sql
roboger/resources/sql/subscription.delete.sql
roboger/resources/sql/subscription.get.sql
roboger/resources/sql/subscription.list.sql
roboger/resources/sql/subscription.update.sql