Metadata-Version: 2.1
Name: roboger
Version: 2.0.45
Summary: Roboger server
Home-page: https://github.com/alttch/roboger
Author: Altertech
Author-email: pr@altertech.com
License: Apache License 2.0
Platform: UNKNOWN
Classifier: Programming Language :: Python :: 3
Classifier: License :: OSI Approved :: Apache Software License
Classifier: Topic :: Communications
License-File: LICENSE
